{"expireTime":9007200908525413000,"key":"transformer-remark-markdown-html-ast-360889ec5010ffef3994328abcb83e6d--","val":{"type":"root","children":[{"type":"element","tagName":"h2","properties":{},"children":[{"type":"text","value":"Insert Into Array","position":{"start":{"line":3,"column":4,"offset":5},"end":{"line":3,"column":21,"offset":22}}}],"position":{"start":{"line":3,"column":1,"offset":2},"end":{"line":3,"column":21,"offset":22}}},{"type":"text","value":"\n"},{"type":"element","tagName":"p","properties":{},"children":[{"type":"text","value":"We have some ","position":{"start":{"line":5,"column":1,"offset":24},"end":{"line":5,"column":14,"offset":37}}},{"type":"element","tagName":"code","properties":{},"children":[{"type":"text","value":"in-built methods"}],"position":{"start":{"line":5,"column":14,"offset":37},"end":{"line":5,"column":32,"offset":55}}},{"type":"text","value":" to add at elements at the beginning and end of the array.","position":{"start":{"line":5,"column":32,"offset":55},"end":{"line":5,"column":90,"offset":113}}}],"position":{"start":{"line":5,"column":1,"offset":24},"end":{"line":5,"column":90,"offset":113}}},{"type":"text","value":"\n"},{"type":"element","tagName":"p","properties":{},"children":[{"type":"element","tagName":"code","properties":{},"children":[{"type":"text","value":"push(value)"}],"position":{"start":{"line":7,"column":1,"offset":115},"end":{"line":7,"column":14,"offset":128}}},{"type":"text","value":" → Add an element to the end of the array.","position":{"start":{"line":7,"column":14,"offset":128},"end":{"line":7,"column":56,"offset":170}}}],"position":{"start":{"line":7,"column":1,"offset":115},"end":{"line":7,"column":56,"offset":170}}},{"type":"text","value":"\n"},{"type":"element","tagName":"p","properties":{},"children":[{"type":"element","tagName":"code","properties":{},"children":[{"type":"text","value":"unshift(value)"}],"position":{"start":{"line":9,"column":1,"offset":172},"end":{"line":9,"column":17,"offset":188}}},{"type":"text","value":" → Add an element to the beginning of an array.","position":{"start":{"line":9,"column":17,"offset":188},"end":{"line":9,"column":64,"offset":235}}}],"position":{"start":{"line":9,"column":1,"offset":172},"end":{"line":9,"column":64,"offset":235}}},{"type":"text","value":"\n"},{"type":"element","tagName":"p","properties":{},"children":[{"type":"text","value":"To add an element to the specific index there is no method available in ","position":{"start":{"line":11,"column":1,"offset":237},"end":{"line":11,"column":73,"offset":309}}},{"type":"element","tagName":"code","properties":{},"children":[{"type":"text","value":"Array"}],"position":{"start":{"line":11,"column":73,"offset":309},"end":{"line":11,"column":80,"offset":316}}},{"type":"text","value":" object. But we can use already available ","position":{"start":{"line":11,"column":80,"offset":316},"end":{"line":11,"column":122,"offset":358}}},{"type":"element","tagName":"code","properties":{},"children":[{"type":"text","value":"splice"}],"position":{"start":{"line":11,"column":122,"offset":358},"end":{"line":11,"column":130,"offset":366}}},{"type":"text","value":" method in ","position":{"start":{"line":11,"column":130,"offset":366},"end":{"line":11,"column":141,"offset":377}}},{"type":"element","tagName":"code","properties":{},"children":[{"type":"text","value":"Array"}],"position":{"start":{"line":11,"column":141,"offset":377},"end":{"line":11,"column":148,"offset":384}}},{"type":"text","value":" object to achieve this.","position":{"start":{"line":11,"column":148,"offset":384},"end":{"line":11,"column":172,"offset":408}}}],"position":{"start":{"line":11,"column":1,"offset":237},"end":{"line":11,"column":172,"offset":408}}},{"type":"text","value":"\n"},{"type":"element","tagName":"p","properties":{},"children":[{"type":"text","value":"An array starts from ","position":{"start":{"line":13,"column":1,"offset":410},"end":{"line":13,"column":22,"offset":431}}},{"type":"element","tagName":"code","properties":{},"children":[{"type":"text","value":"index 0"}],"position":{"start":{"line":13,"column":22,"offset":431},"end":{"line":13,"column":31,"offset":440}}},{"type":"text","value":" ,So if we want to add an element as first element of the array , then the index of the element is ","position":{"start":{"line":13,"column":31,"offset":440},"end":{"line":13,"column":130,"offset":539}}},{"type":"element","tagName":"code","properties":{},"children":[{"type":"text","value":"0"}],"position":{"start":{"line":13,"column":130,"offset":539},"end":{"line":13,"column":133,"offset":542}}},{"type":"text","value":" .If we want to add an element to ","position":{"start":{"line":13,"column":133,"offset":542},"end":{"line":13,"column":167,"offset":576}}},{"type":"element","tagName":"code","properties":{},"children":[{"type":"text","value":"nth"}],"position":{"start":{"line":13,"column":167,"offset":576},"end":{"line":13,"column":172,"offset":581}}},{"type":"text","value":" position , then the index is ","position":{"start":{"line":13,"column":172,"offset":581},"end":{"line":13,"column":202,"offset":611}}},{"type":"element","tagName":"code","properties":{},"children":[{"type":"text","value":"(n-1) th"}],"position":{"start":{"line":13,"column":202,"offset":611},"end":{"line":13,"column":212,"offset":621}}},{"type":"text","value":" index.","position":{"start":{"line":13,"column":212,"offset":621},"end":{"line":13,"column":219,"offset":628}}}],"position":{"start":{"line":13,"column":1,"offset":410},"end":{"line":13,"column":219,"offset":628}}},{"type":"text","value":"\n"},{"type":"element","tagName":"p","properties":{},"children":[{"type":"text","value":"MDN : The splice() method changes the contents of an array by removing or replacing existing elements and/or adding new elements, in the original array(which means the source array is modified)","position":{"start":{"line":15,"column":1,"offset":630},"end":{"line":15,"column":194,"offset":823}}}],"position":{"start":{"line":15,"column":1,"offset":630},"end":{"line":15,"column":194,"offset":823}}},{"type":"text","value":"\n"},{"type":"element","tagName":"p","properties":{},"children":[{"type":"element","tagName":"code","properties":{},"children":[{"type":"text","value":"splice()"}],"position":{"start":{"line":17,"column":1,"offset":825},"end":{"line":17,"column":11,"offset":835}}},{"type":"text","value":" method takes three argument","position":{"start":{"line":17,"column":11,"offset":835},"end":{"line":17,"column":39,"offset":863}}}],"position":{"start":{"line":17,"column":1,"offset":825},"end":{"line":17,"column":39,"offset":863}}},{"type":"text","value":"\n"},{"type":"element","tagName":"ol","properties":{},"children":[{"type":"text","value":"\n"},{"type":"element","tagName":"li","properties":{},"children":[{"type":"element","tagName":"em","properties":{},"children":[{"type":"text","value":"start\\","position":{"start":{"line":19,"column":6,"offset":870},"end":{"line":19,"column":12,"offset":876}}}],"position":{"start":{"line":19,"column":5,"offset":869},"end":{"line":19,"column":13,"offset":877}}},{"type":"text","value":"*","position":{"start":{"line":19,"column":13,"offset":877},"end":{"line":19,"column":15,"offset":879}}},{"type":"text","value":" → *The index at which to start changing the array.","position":{"start":{"line":19,"column":15,"offset":879},"end":{"line":19,"column":66,"offset":930}}}],"position":{"start":{"line":19,"column":1,"offset":865},"end":{"line":19,"column":66,"offset":930}}},{"type":"text","value":"\n"},{"type":"element","tagName":"li","properties":{},"children":[{"type":"text","value":"*deleteCount(optional) → *An integer indicating the number of elements in the array to remove from ","position":{"start":{"line":20,"column":5,"offset":935},"end":{"line":20,"column":104,"offset":1034}}},{"type":"element","tagName":"code","properties":{},"children":[{"type":"text","value":"start"}],"position":{"start":{"line":20,"column":104,"offset":1034},"end":{"line":20,"column":111,"offset":1041}}},{"type":"text","value":".","position":{"start":{"line":20,"column":111,"offset":1041},"end":{"line":20,"column":112,"offset":1042}}}],"position":{"start":{"line":20,"column":1,"offset":931},"end":{"line":20,"column":112,"offset":1042}}},{"type":"text","value":"\n"},{"type":"element","tagName":"li","properties":{},"children":[{"type":"text","value":"*(elem1, elem2 ...) → *The elements to add to the array, beginning from ","position":{"start":{"line":21,"column":5,"offset":1047},"end":{"line":21,"column":77,"offset":1119}}},{"type":"element","tagName":"code","properties":{},"children":[{"type":"text","value":"start"}],"position":{"start":{"line":21,"column":77,"offset":1119},"end":{"line":21,"column":84,"offset":1126}}},{"type":"text","value":". If you do not specify any elements, ","position":{"start":{"line":21,"column":84,"offset":1126},"end":{"line":21,"column":122,"offset":1164}}},{"type":"element","tagName":"code","properties":{},"children":[{"type":"text","value":"splice()"}],"position":{"start":{"line":21,"column":122,"offset":1164},"end":{"line":21,"column":132,"offset":1174}}},{"type":"text","value":" will only remove elements from the array.","position":{"start":{"line":21,"column":132,"offset":1174},"end":{"line":21,"column":174,"offset":1216}}}],"position":{"start":{"line":21,"column":1,"offset":1043},"end":{"line":21,"column":174,"offset":1216}}},{"type":"text","value":"\n"}],"position":{"start":{"line":19,"column":1,"offset":865},"end":{"line":21,"column":174,"offset":1216}}},{"type":"text","value":"\n"},{"type":"element","tagName":"p","properties":{},"children":[{"type":"text","value":"In order to insert an element to the specific index , we need to provide arguments as","position":{"start":{"line":23,"column":1,"offset":1218},"end":{"line":23,"column":86,"offset":1303}}}],"position":{"start":{"line":23,"column":1,"offset":1218},"end":{"line":23,"column":86,"offset":1303}}},{"type":"text","value":"\n"},{"type":"element","tagName":"ol","properties":{},"children":[{"type":"text","value":"\n"},{"type":"element","tagName":"li","properties":{},"children":[{"type":"element","tagName":"code","properties":{},"children":[{"type":"text","value":"start"}],"position":{"start":{"line":25,"column":5,"offset":1309},"end":{"line":25,"column":12,"offset":1316}}},{"type":"text","value":" → ","position":{"start":{"line":25,"column":12,"offset":1316},"end":{"line":25,"column":15,"offset":1319}}},{"type":"element","tagName":"code","properties":{},"children":[{"type":"text","value":"index"}],"position":{"start":{"line":25,"column":15,"offset":1319},"end":{"line":25,"column":22,"offset":1326}}},{"type":"text","value":" where to insert the element","position":{"start":{"line":25,"column":22,"offset":1326},"end":{"line":25,"column":50,"offset":1354}}}],"position":{"start":{"line":25,"column":1,"offset":1305},"end":{"line":25,"column":50,"offset":1354}}},{"type":"text","value":"\n"},{"type":"element","tagName":"li","properties":{},"children":[{"type":"element","tagName":"code","properties":{},"children":[{"type":"text","value":"deleteCount"}],"position":{"start":{"line":26,"column":5,"offset":1359},"end":{"line":26,"column":18,"offset":1372}}},{"type":"text","value":" → ","position":{"start":{"line":26,"column":18,"offset":1372},"end":{"line":26,"column":21,"offset":1375}}},{"type":"element","tagName":"code","properties":{},"children":[{"type":"text","value":"0"}],"position":{"start":{"line":26,"column":21,"offset":1375},"end":{"line":26,"column":24,"offset":1378}}},{"type":"text","value":" (because we don't need to delete element)","position":{"start":{"line":26,"column":24,"offset":1378},"end":{"line":26,"column":66,"offset":1420}}}],"position":{"start":{"line":26,"column":1,"offset":1355},"end":{"line":26,"column":66,"offset":1420}}},{"type":"text","value":"\n"},{"type":"element","tagName":"li","properties":{},"children":[{"type":"element","tagName":"code","properties":{},"children":[{"type":"text","value":"elem"}],"position":{"start":{"line":27,"column":5,"offset":1425},"end":{"line":27,"column":11,"offset":1431}}},{"type":"text","value":" → elements to insert","position":{"start":{"line":27,"column":11,"offset":1431},"end":{"line":27,"column":32,"offset":1452}}}],"position":{"start":{"line":27,"column":1,"offset":1421},"end":{"line":27,"column":32,"offset":1452}}},{"type":"text","value":"\n"}],"position":{"start":{"line":25,"column":1,"offset":1305},"end":{"line":27,"column":32,"offset":1452}}},{"type":"text","value":"\n"},{"type":"element","tagName":"p","properties":{},"children":[{"type":"text","value":"Let's Write the function","position":{"start":{"line":29,"column":1,"offset":1454},"end":{"line":29,"column":25,"offset":1478}}},{"type":"element","tagName":"br","properties":{},"children":[],"position":{"start":{"line":29,"column":25,"offset":1478},"end":{"line":30,"column":1,"offset":1480}}},{"type":"text","value":"\n"},{"type":"text","value":"function insertAt(array, index, ...elementsArray) { array.splice(index, 0, ...elements);}","position":{"start":{"line":30,"column":1,"offset":1480},"end":{"line":30,"column":90,"offset":1569}}}],"position":{"start":{"line":29,"column":1,"offset":1454},"end":{"line":30,"column":90,"offset":1569}}},{"type":"text","value":"\n"},{"type":"element","tagName":"p","properties":{},"children":[{"type":"text","value":"Now Let's call the function","position":{"start":{"line":32,"column":1,"offset":1571},"end":{"line":32,"column":28,"offset":1598}}}],"position":{"start":{"line":32,"column":1,"offset":1571},"end":{"line":32,"column":28,"offset":1598}}},{"type":"text","value":"\n"},{"type":"element","tagName":"p","properties":{},"children":[{"type":"text","value":"var num = ","position":{"start":{"line":34,"column":1,"offset":1600},"end":{"line":34,"column":11,"offset":1610}}},{"type":"text","value":"[1,2,3,6,7,8]","position":{"start":{"line":34,"column":12,"offset":1611},"end":{"line":34,"column":23,"offset":1622}}},{"type":"text","value":";/","position":{"start":{"line":34,"column":24,"offset":1623},"end":{"line":34,"column":26,"offset":1625}}},{"type":"text","value":"*","position":{"start":{"line":34,"column":26,"offset":1625},"end":{"line":34,"column":28,"offset":1627}}},{"type":"element","tagName":"br","properties":{},"children":[],"position":{"start":{"line":34,"column":28,"offset":1627},"end":{"line":35,"column":1,"offset":1629}}},{"type":"text","value":"\n"},{"type":"text","value":"arguments\\","position":{"start":{"line":35,"column":1,"offset":1629},"end":{"line":35,"column":12,"offset":1640}}}],"position":{"start":{"line":34,"column":1,"offset":1600},"end":{"line":35,"column":12,"offset":1640}}},{"type":"text","value":"\n"},{"type":"element","tagName":"ul","properties":{},"children":[{"type":"text","value":"\n"},{"type":"element","tagName":"li","properties":{},"children":[{"type":"text","value":"\n"},{"type":"element","tagName":"ol","properties":{},"children":[{"type":"text","value":"\n"},{"type":"element","tagName":"li","properties":{},"children":[{"type":"text","value":"source array - num\\","position":{"start":{"line":37,"column":6,"offset":1647},"end":{"line":37,"column":25,"offset":1666}}}],"position":{"start":{"line":37,"column":3,"offset":1644},"end":{"line":37,"column":25,"offset":1666}}},{"type":"text","value":"\n"}],"position":{"start":{"line":37,"column":3,"offset":1644},"end":{"line":37,"column":25,"offset":1666}}},{"type":"text","value":"\n"}],"position":{"start":{"line":37,"column":1,"offset":1642},"end":{"line":37,"column":25,"offset":1666}}},{"type":"text","value":"\n"},{"type":"element","tagName":"li","properties":{},"children":[{"type":"text","value":"\n"},{"type":"element","tagName":"ol","properties":{"start":2},"children":[{"type":"text","value":"\n"},{"type":"element","tagName":"li","properties":{},"children":[{"type":"text","value":"index to insert - 3\\","position":{"start":{"line":38,"column":6,"offset":1672},"end":{"line":38,"column":26,"offset":1692}}}],"position":{"start":{"line":38,"column":3,"offset":1669},"end":{"line":38,"column":26,"offset":1692}}},{"type":"text","value":"\n"}],"position":{"start":{"line":38,"column":3,"offset":1669},"end":{"line":38,"column":26,"offset":1692}}},{"type":"text","value":"\n"}],"position":{"start":{"line":38,"column":1,"offset":1667},"end":{"line":38,"column":26,"offset":1692}}},{"type":"text","value":"\n"},{"type":"element","tagName":"li","properties":{},"children":[{"type":"text","value":"\n"},{"type":"element","tagName":"ol","properties":{"start":3},"children":[{"type":"text","value":"\n"},{"type":"element","tagName":"li","properties":{},"children":[{"type":"text","value":"remaining are elements to insert","position":{"start":{"line":39,"column":6,"offset":1698},"end":{"line":39,"column":38,"offset":1730}}},{"type":"element","tagName":"br","properties":{},"children":[],"position":{"start":{"line":39,"column":38,"offset":1730},"end":{"line":40,"column":8,"offset":1739}}},{"type":"text","value":"\n"},{"type":"text","value":"*","position":{"start":{"line":40,"column":8,"offset":1739},"end":{"line":40,"column":10,"offset":1741}}},{"type":"text","value":"/insertAt(num, 3, 4, 5); // ","position":{"start":{"line":40,"column":10,"offset":1741},"end":{"line":40,"column":38,"offset":1769}}},{"type":"text","value":"[1,2,3,4,5,6,7,8]","position":{"start":{"line":40,"column":39,"offset":1770},"end":{"line":40,"column":54,"offset":1785}}},{"type":"element","tagName":"strong","properties":{},"children":[{"type":"text","value":"**","position":{"start":{"line":40,"column":57,"offset":1788},"end":{"line":40,"column":59,"offset":1790}}}],"position":{"start":{"line":40,"column":55,"offset":1786},"end":{"line":40,"column":61,"offset":1792}}},{"type":"text","value":"*","position":{"start":{"line":40,"column":61,"offset":1792},"end":{"line":40,"column":63,"offset":1794}}},{"type":"text","value":"*","position":{"start":{"line":40,"column":63,"offset":1794},"end":{"line":40,"column":65,"offset":1796}}},{"type":"element","tagName":"strong","properties":{},"children":[{"type":"text","value":"**","position":{"start":{"line":40,"column":67,"offset":1798},"end":{"line":40,"column":69,"offset":1800}}}],"position":{"start":{"line":40,"column":65,"offset":1796},"end":{"line":40,"column":71,"offset":1802}}},{"type":"text","value":"*","position":{"start":{"line":40,"column":71,"offset":1802},"end":{"line":40,"column":73,"offset":1804}}},{"type":"text","value":"*","position":{"start":{"line":40,"column":73,"offset":1804},"end":{"line":40,"column":75,"offset":1806}}},{"type":"element","tagName":"strong","properties":{},"children":[{"type":"text","value":"**","position":{"start":{"line":40,"column":77,"offset":1808},"end":{"line":40,"column":79,"offset":1810}}}],"position":{"start":{"line":40,"column":75,"offset":1806},"end":{"line":40,"column":81,"offset":1812}}},{"type":"text","value":"*","position":{"start":{"line":40,"column":81,"offset":1812},"end":{"line":40,"column":83,"offset":1814}}},{"type":"text","value":"*","position":{"start":{"line":40,"column":83,"offset":1814},"end":{"line":40,"column":85,"offset":1816}}},{"type":"element","tagName":"strong","properties":{},"children":[{"type":"text","value":"**","position":{"start":{"line":40,"column":87,"offset":1818},"end":{"line":40,"column":89,"offset":1820}}}],"position":{"start":{"line":40,"column":85,"offset":1816},"end":{"line":40,"column":91,"offset":1822}}},{"type":"text","value":"_","position":{"start":{"line":40,"column":91,"offset":1822},"end":{"line":40,"column":93,"offset":1824}}},{"type":"text","value":"_","position":{"start":{"line":40,"column":93,"offset":1824},"end":{"line":40,"column":95,"offset":1826}}},{"type":"text","value":"_","position":{"start":{"line":40,"column":95,"offset":1826},"end":{"line":40,"column":97,"offset":1828}}},{"type":"text","value":"_","position":{"start":{"line":40,"column":97,"offset":1828},"end":{"line":40,"column":99,"offset":1830}}},{"type":"element","tagName":"strong","properties":{},"children":[{"type":"text","value":"**","position":{"start":{"line":40,"column":101,"offset":1832},"end":{"line":40,"column":103,"offset":1834}}}],"position":{"start":{"line":40,"column":99,"offset":1830},"end":{"line":40,"column":105,"offset":1836}}},{"type":"text","value":"*","position":{"start":{"line":40,"column":105,"offset":1836},"end":{"line":40,"column":107,"offset":1838}}},{"type":"text","value":"*","position":{"start":{"line":40,"column":107,"offset":1838},"end":{"line":40,"column":109,"offset":1840}}},{"type":"element","tagName":"strong","properties":{},"children":[{"type":"text","value":"**","position":{"start":{"line":40,"column":111,"offset":1842},"end":{"line":40,"column":113,"offset":1844}}}],"position":{"start":{"line":40,"column":109,"offset":1840},"end":{"line":40,"column":115,"offset":1846}}},{"type":"text","value":"*","position":{"start":{"line":40,"column":115,"offset":1846},"end":{"line":40,"column":117,"offset":1848}}},{"type":"text","value":"*","position":{"start":{"line":40,"column":117,"offset":1848},"end":{"line":40,"column":119,"offset":1850}}},{"type":"element","tagName":"strong","properties":{},"children":[{"type":"text","value":"**","position":{"start":{"line":40,"column":121,"offset":1852},"end":{"line":40,"column":123,"offset":1854}}}],"position":{"start":{"line":40,"column":119,"offset":1850},"end":{"line":40,"column":125,"offset":1856}}},{"type":"text","value":"*","position":{"start":{"line":40,"column":125,"offset":1856},"end":{"line":40,"column":127,"offset":1858}}},{"type":"text","value":"*","position":{"start":{"line":40,"column":127,"offset":1858},"end":{"line":40,"column":129,"offset":1860}}},{"type":"element","tagName":"strong","properties":{},"children":[{"type":"text","value":"**","position":{"start":{"line":40,"column":131,"offset":1862},"end":{"line":40,"column":133,"offset":1864}}}],"position":{"start":{"line":40,"column":129,"offset":1860},"end":{"line":40,"column":135,"offset":1866}}},{"type":"text","value":"// let's try changing the indexvar num = ","position":{"start":{"line":40,"column":135,"offset":1866},"end":{"line":40,"column":176,"offset":1907}}},{"type":"text","value":"[1,2,3,6,7,8]","position":{"start":{"line":40,"column":177,"offset":1908},"end":{"line":40,"column":188,"offset":1919}}},{"type":"text","value":";insertAt(numbers, 2, 4,5); // ","position":{"start":{"line":40,"column":189,"offset":1920},"end":{"line":40,"column":220,"offset":1951}}},{"type":"text","value":"[1,2,4,5,3,6,7,8]","position":{"start":{"line":40,"column":221,"offset":1952},"end":{"line":40,"column":236,"offset":1967}}}],"position":{"start":{"line":39,"column":3,"offset":1695},"end":{"line":40,"column":237,"offset":1968}}},{"type":"text","value":"\n"}],"position":{"start":{"line":39,"column":3,"offset":1695},"end":{"line":40,"column":237,"offset":1968}}},{"type":"text","value":"\n"}],"position":{"start":{"line":39,"column":1,"offset":1693},"end":{"line":40,"column":237,"offset":1968}}},{"type":"text","value":"\n"}],"position":{"start":{"line":37,"column":1,"offset":1642},"end":{"line":40,"column":237,"offset":1968}}}],"position":{"start":{"line":1,"column":1,"offset":0},"end":{"line":41,"column":1,"offset":1969}}}}